Metadata-Version: 2.1
Name: GMGC-mapper
Version: 0.1.0
Summary: Map genes and genome to the Global Microbial Gene Catalog (GMGC)
Home-page: https://github.com/psj1997/GMGC_mapper
Author: Shaojun Pan
Author-email: shaojun1997777@gmail.com
License: MIT
Platform: UNKNOWN
Classifier: License :: OSI Approved :: MIT License
Classifier: Programming Language :: Python :: 3.6
Classifier: Programming Language :: Python :: 3.7
Classifier: Programming Language :: Python :: 3.8
